<?xml version="1.0" encoding="UTF-8"?>
<!DOCTYPE mapper PUBLIC "-//mybatis.org//DTD Mapper 3.0//EN" "http://mybatis.org/dtd/mybatis-3-mapper.dtd">
<mapper namespace="com.xdc.sparrowShop.generate.UserMapper">
  <resultMap id="BaseResultMap" type="com.xdc.sparrowShop.generate.User">
    <!--
      WARNING - @mbg.generated
      This element is automatically generated by MyBatis Generator, do not modify.
      This element was generated on Sat May 02 15:12:52 CST 2020.
    -->
    <id column="ID" jdbcType="INTEGER" property="id" />
    <result column="OPENID" jdbcType="VARCHAR" property="openid" />
    <result column="NICK_NAME" jdbcType="VARCHAR" property="nickName" />
    <result column="ACCOUNT" jdbcType="INTEGER" property="account" />
    <result column="AVATAR" jdbcType="VARCHAR" property="avatar" />
    <result column="CREATED_AT" jdbcType="TIMESTAMP" property="createdAt" />
    <result column="UPDATED_AT" jdbcType="TIMESTAMP" property="updatedAt" />
  </resultMap>
  <sql id="Example_Where_Clause">
    <!--
      WARNING - @mbg.generated
      This element is automatically generated by MyBatis Generator, do not modify.
      This element was generated on Sat May 02 15:12:52 CST 2020.
    -->
    <where>
      <foreach collection="oredCriteria" item="criteria" separator="or">
        <if test="criteria.valid">
          <trim prefix="(" prefixOverrides="and" suffix=")">
            <foreach collection="criteria.criteria" item="criterion">
              <choose>
                <when test="criterion.noValue">
                  and ${criterion.condition}
                </when>
                <when test="criterion.singleValue">
                  and ${criterion.condition} #{criterion.value}
                </when>
                <when test="criterion.betweenValue">
                  and ${criterion.condition} #{criterion.value} and #{criterion.secondValue}
                </when>
                <when test="criterion.listValue">
                  and ${criterion.condition}
                  <foreach close=")" collection="criterion.value" item="listItem" open="(" separator=",">
                    #{listItem}
                  </foreach>
                </when>
              </choose>
            </foreach>
          </trim>
        </if>
      </foreach>
    </where>
  </sql>
  <sql id="Update_By_Example_Where_Clause">
    <!--
      WARNING - @mbg.generated
      This element is automatically generated by MyBatis Generator, do not modify.
      This element was generated on Sat May 02 15:12:52 CST 2020.
    -->
    <where>
      <foreach collection="example.oredCriteria" item="criteria" separator="or">
        <if test="criteria.valid">
          <trim prefix="(" prefixOverrides="and" suffix=")">
            <foreach collection="criteria.criteria" item="criterion">
              <choose>
                <when test="criterion.noValue">
                  and ${criterion.condition}
                </when>
                <when test="criterion.singleValue">
                  and ${criterion.condition} #{criterion.value}
                </when>
                <when test="criterion.betweenValue">
                  and ${criterion.condition} #{criterion.value} and #{criterion.secondValue}
                </when>
                <when test="criterion.listValue">
                  and ${criterion.condition}
                  <foreach close=")" collection="criterion.value" item="listItem" open="(" separator=",">
                    #{listItem}
                  </foreach>
                </when>
              </choose>
            </foreach>
          </trim>
        </if>
      </foreach>
    </where>
  </sql>
  <sql id="Base_Column_List">
    <!--
      WARNING - @mbg.generated
      This element is automatically generated by MyBatis Generator, do not modify.
      This element was generated on Sat May 02 15:12:52 CST 2020.
    -->
    ID, OPENID, NICK_NAME, ACCOUNT, AVATAR, CREATED_AT, UPDATED_AT
  </sql>
  <select id="selectByExample" parameterType="com.xdc.sparrowShop.generate.UserExample" resultMap="BaseResultMap">
    <!--
      WARNING - @mbg.generated
      This element is automatically generated by MyBatis Generator, do not modify.
      This element was generated on Sat May 02 15:12:52 CST 2020.
    -->
    select
    <if test="distinct">
      distinct
    </if>
    <include refid="Base_Column_List" />
    from USER
    <if test="_parameter != null">
      <include refid="Example_Where_Clause" />
    </if>
    <if test="orderByClause != null">
      order by ${orderByClause}
    </if>
    <if test="limit != null">
      <if test="offset != null">
        limit ${offset}, ${limit}
      </if>
      <if test="offset == null">
        limit ${limit}
      </if>
    </if>
  </select>
  <select id="selectByPrimaryKey" parameterType="java.lang.Integer" resultMap="BaseResultMap">
    <!--
      WARNING - @mbg.generated
      This element is automatically generated by MyBatis Generator, do not modify.
      This element was generated on Sat May 02 15:12:52 CST 2020.
    -->
    select 
    <include refid="Base_Column_List" />
    from USER
    where ID = #{id,jdbcType=INTEGER}
  </select>
  <delete id="deleteByPrimaryKey" parameterType="java.lang.Integer">
    <!--
      WARNING - @mbg.generated
      This element is automatically generated by MyBatis Generator, do not modify.
      This element was generated on Sat May 02 15:12:52 CST 2020.
    -->
    delete from USER
    where ID = #{id,jdbcType=INTEGER}
  </delete>
  <delete id="deleteByExample" parameterType="com.xdc.sparrowShop.generate.UserExample">
    <!--
      WARNING - @mbg.generated
      This element is automatically generated by MyBatis Generator, do not modify.
      This element was generated on Sat May 02 15:12:52 CST 2020.
    -->
    delete from USER
    <if test="_parameter != null">
      <include refid="Example_Where_Clause" />
    </if>
  </delete>
  <insert id="insert" parameterType="com.xdc.sparrowShop.generate.User">
    <!--
      WARNING - @mbg.generated
      This element is automatically generated by MyBatis Generator, do not modify.
      This element was generated on Sat May 02 15:12:52 CST 2020.
    -->
    <selectKey keyProperty="id" order="AFTER" resultType="java.lang.Integer">
      SELECT LAST_INSERT_ID()
    </selectKey>
    insert into USER (OPENID, NICK_NAME, ACCOUNT, 
      AVATAR, CREATED_AT, UPDATED_AT
      )
    values (#{openid,jdbcType=VARCHAR}, #{nickName,jdbcType=VARCHAR}, #{account,jdbcType=INTEGER}, 
      #{avatar,jdbcType=VARCHAR}, #{createdAt,jdbcType=TIMESTAMP}, #{updatedAt,jdbcType=TIMESTAMP}
      )
  </insert>
  <insert id="insertSelective" parameterType="com.xdc.sparrowShop.generate.User">
    <!--
      WARNING - @mbg.generated
      This element is automatically generated by MyBatis Generator, do not modify.
      This element was generated on Sat May 02 15:12:52 CST 2020.
    -->
    <selectKey keyProperty="id" order="AFTER" resultType="java.lang.Integer">
      SELECT LAST_INSERT_ID()
    </selectKey>
    insert into USER
    <trim prefix="(" suffix=")" suffixOverrides=",">
      <if test="openid != null">
        OPENID,
      </if>
      <if test="nickName != null">
        NICK_NAME,
      </if>
      <if test="account != null">
        ACCOUNT,
      </if>
      <if test="avatar != null">
        AVATAR,
      </if>
      <if test="createdAt != null">
        CREATED_AT,
      </if>
      <if test="updatedAt != null">
        UPDATED_AT,
      </if>
    </trim>
    <trim prefix="values (" suffix=")" suffixOverrides=",">
      <if test="openid != null">
        #{openid,jdbcType=VARCHAR},
      </if>
      <if test="nickName != null">
        #{nickName,jdbcType=VARCHAR},
      </if>
      <if test="account != null">
        #{account,jdbcType=INTEGER},
      </if>
      <if test="avatar != null">
        #{avatar,jdbcType=VARCHAR},
      </if>
      <if test="createdAt != null">
        #{createdAt,jdbcType=TIMESTAMP},
      </if>
      <if test="updatedAt != null">
        #{updatedAt,jdbcType=TIMESTAMP},
      </if>
    </trim>
  </insert>
  <select id="countByExample" parameterType="com.xdc.sparrowShop.generate.UserExample" resultType="java.lang.Long">
    <!--
      WARNING - @mbg.generated
      This element is automatically generated by MyBatis Generator, do not modify.
      This element was generated on Sat May 02 15:12:52 CST 2020.
    -->
    select count(*) from USER
    <if test="_parameter != null">
      <include refid="Example_Where_Clause" />
    </if>
  </select>
  <update id="updateByExampleSelective" parameterType="map">
    <!--
      WARNING - @mbg.generated
      This element is automatically generated by MyBatis Generator, do not modify.
      This element was generated on Sat May 02 15:12:52 CST 2020.
    -->
    update USER
    <set>
      <if test="record.id != null">
        ID = #{record.id,jdbcType=INTEGER},
      </if>
      <if test="record.openid != null">
        OPENID = #{record.openid,jdbcType=VARCHAR},
      </if>
      <if test="record.nickName != null">
        NICK_NAME = #{record.nickName,jdbcType=VARCHAR},
      </if>
      <if test="record.account != null">
        ACCOUNT = #{record.account,jdbcType=INTEGER},
      </if>
      <if test="record.avatar != null">
        AVATAR = #{record.avatar,jdbcType=VARCHAR},
      </if>
      <if test="record.createdAt != null">
        CREATED_AT = #{record.createdAt,jdbcType=TIMESTAMP},
      </if>
      <if test="record.updatedAt != null">
        UPDATED_AT = #{record.updatedAt,jdbcType=TIMESTAMP},
      </if>
    </set>
    <if test="_parameter != null">
      <include refid="Update_By_Example_Where_Clause" />
    </if>
  </update>
  <update id="updateByExample" parameterType="map">
    <!--
      WARNING - @mbg.generated
      This element is automatically generated by MyBatis Generator, do not modify.
      This element was generated on Sat May 02 15:12:52 CST 2020.
    -->
    update USER
    set ID = #{record.id,jdbcType=INTEGER},
      OPENID = #{record.openid,jdbcType=VARCHAR},
      NICK_NAME = #{record.nickName,jdbcType=VARCHAR},
      ACCOUNT = #{record.account,jdbcType=INTEGER},
      AVATAR = #{record.avatar,jdbcType=VARCHAR},
      CREATED_AT = #{record.createdAt,jdbcType=TIMESTAMP},
      UPDATED_AT = #{record.updatedAt,jdbcType=TIMESTAMP}
    <if test="_parameter != null">
      <include refid="Update_By_Example_Where_Clause" />
    </if>
  </update>
  <update id="updateByPrimaryKeySelective" parameterType="com.xdc.sparrowShop.generate.User">
    <!--
      WARNING - @mbg.generated
      This element is automatically generated by MyBatis Generator, do not modify.
      This element was generated on Sat May 02 15:12:52 CST 2020.
    -->
    update USER
    <set>
      <if test="openid != null">
        OPENID = #{openid,jdbcType=VARCHAR},
      </if>
      <if test="nickName != null">
        NICK_NAME = #{nickName,jdbcType=VARCHAR},
      </if>
      <if test="account != null">
        ACCOUNT = #{account,jdbcType=INTEGER},
      </if>
      <if test="avatar != null">
        AVATAR = #{avatar,jdbcType=VARCHAR},
      </if>
      <if test="createdAt != null">
        CREATED_AT = #{createdAt,jdbcType=TIMESTAMP},
      </if>
      <if test="updatedAt != null">
        UPDATED_AT = #{updatedAt,jdbcType=TIMESTAMP},
      </if>
    </set>
    where ID = #{id,jdbcType=INTEGER}
  </update>
  <update id="updateByPrimaryKey" parameterType="com.xdc.sparrowShop.generate.User">
    <!--
      WARNING - @mbg.generated
      This element is automatically generated by MyBatis Generator, do not modify.
      This element was generated on Sat May 02 15:12:52 CST 2020.
    -->
    update USER
    set OPENID = #{openid,jdbcType=VARCHAR},
      NICK_NAME = #{nickName,jdbcType=VARCHAR},
      ACCOUNT = #{account,jdbcType=INTEGER},
      AVATAR = #{avatar,jdbcType=VARCHAR},
      CREATED_AT = #{createdAt,jdbcType=TIMESTAMP},
      UPDATED_AT = #{updatedAt,jdbcType=TIMESTAMP}
    where ID = #{id,jdbcType=INTEGER}
  </update>
</mapper>